[
    {
        "id": "23ad93e0-3669-4524-84ab-c81d886e787d",
        "image": "23ad93e0-3669-4524-84ab-c81d886e787d.jpg",
        "conversations": [
            {
                "from": "human",
                "value": "What is the main theme depicted in the paintings of Ajanta Caves?"
            },
            {
                "from": "gpt",
                "value": "The main theme depicted in the paintings of Ajanta Caves is the life of Buddha and various Jataka tales."
            }
        ]
    },
    {
        "id": "50126e85-8806-4d7e-be87-6415f4805e4b",
        "image": "50126e85-8806-4d7e-be87-6415f4805e4b.jpg",
        "conversations": [
            {
                "from": "human",
                "value": "What is the most prominent feature of the Ellora Caves?"
            },
            {
                "from": "gpt",
                "value": "The most prominent feature of the Ellora Caves is the monolithic Kailasa Temple dedicated to Lord Shiva."
            }
        ]
    },
    {
        "id": "db7c8677-06a4-46cf-9988-0927b2a7a461",
        "image": "db7c8677-06a4-46cf-9988-0927b2a7a461.jpg",
        "conversations": [
            {
                "from": "human",
                "value": "What is the architectural style of the buildings inside Agra Fort?"
            },
            {
                "from": "gpt",
                "value": "The buildings inside Agra Fort showcase a blend of Islamic, Persian, and Hindu architectural styles."
            }
        ]
    },
    {
        "id": "827b84b5-ece9-413d-a3b4-24deaeefd391",
        "image": "827b84b5-ece9-413d-a3b4-24deaeefd391.jpg",
        "conversations": [
            {
                "from": "human",
                "value": "What is the material used in the construction of the Taj Mahal's dome?"
            },
            {
                "from": "gpt",
                "value": "The dome of the Taj Mahal is constructed using white marble adorned with intricate inlay work of precious and semi-precious stones."
            }
        ]
    },
    {
        "id": "8686773e-905e-4c7c-94a5-140bfa9c15e8",
        "image": "8686773e-905e-4c7c-94a5-140bfa9c15e8.jpg",
        "conversations": [
            {
                "from": "human",
                "value": "What is the significance of the Sun Temple's orientation in Konarak?"
            },
            {
                "from": "gpt",
                "value": "The orientation of the Sun Temple in Konarak is designed to align with the east-west path of the sun, symbolizing the passage of time and the cycle of the day."
            }
        ]
    },
    {
        "id": "e57022a5-61c7-4eb6-8698-1d334c09ac6c",
        "image": "e57022a5-61c7-4eb6-8698-1d334c09ac6c.jpg",
        "conversations": [
            {
                "from": "human",
                "value": "What is the legend associated with the creation of the Shore Temple in Mahabalipuram?"
            },
            {
                "from": "gpt",
                "value": "According to legend, the Shore Temple in Mahabalipuram was created by the Pallava king Narasimhavarman II to commemorate the victory of his naval forces over the Chalukyas."
            }
        ]
    },
    {
        "id": "3f5da132-654c-49bc-8e28-69a9f11a28fb",
        "image": "3f5da132-654c-49bc-8e28-69a9f11a28fb.jpg",
        "conversations": [
            {
                "from": "human",
                "value": "What is the primary habitat of the one-horned rhinoceros in Kaziranga National Park?"
            },
            {
                "from": "gpt",
                "value": "The one-horned rhinoceros in Kaziranga National Park primarily inhabit the tall grasslands and marshes of the park."
            }
        ]
    },
    {
        "id": "113baeea-cd09-4505-bab9-2b34a4ac4a43",
        "image": "113baeea-cd09-4505-bab9-2b34a4ac4a43.jpg",
        "conversations": [
            {
                "from": "human",
                "value": "What is the most sought-after species for wildlife enthusiasts in Manas Wildlife Sanctuary?"
            },
            {
                "from": "gpt",
                "value": "The most sought-after species for wildlife enthusiasts in Manas Wildlife Sanctuary is the Bengal tiger."
            }
        ]
    },
    {
        "id": "e31c9f97-921b-4549-afec-bf52cd89e1a7",
        "image": "e31c9f97-921b-4549-afec-bf52cd89e1a7.jpg",
        "conversations": [
            {
                "from": "human",
                "value": "What is the unique feature of the wetland ecosystem in Keoladeo National Park?"
            },
            {
                "from": "gpt",
                "value": "The unique feature of the wetland ecosystem in Keoladeo National Park is its role as a crucial wintering ground for migratory birds."
            }
        ]
    },
    {
        "id": "8033c919-8356-455b-99e0-465e4aa38791",
        "image": "8033c919-8356-455b-99e0-465e4aa38791.jpg",
        "conversations": [
            {
                "from": "human",
                "value": "What is the architectural style of the churches in the Churches and Convents of Goa?"
            },
            {
                "from": "gpt",
                "value": "The churches in the Churches and Convents of Goa exhibit a blend of Portuguese and Indian architectural styles, characterized by whitewashed facades, ornate interiors, and decorative altars."
            }
        ]
    },
    {
        "id": "9836ed25-edb5-4d5b-8479-55631e1b8f95",
        "image": "9836ed25-edb5-4d5b-8479-55631e1b8f95.jpg",
        "conversations": [
            {
                "from": "human",
                "value": "What is the symbolic significance behind the erotic sculptures of Khajuraho Group of Monuments?"
            },
            {
                "from": "gpt",
                "value": "The erotic sculptures of Khajuraho Group of Monuments symbolize the celebration of life, love, and spiritual awakening."
            }
        ]
    },
    {
        "id": "c00d466f-0f56-42e5-82e0-aa9581996a83",
        "image": "c00d466f-0f56-42e5-82e0-aa9581996a83.jpg",
        "conversations": [
            {
                "from": "human",
                "value": "What was the main function of the Virupaksha Temple in the Group of Monuments at Hampi?"
            },
            {
                "from": "gpt",
                "value": "The main function of the Virupaksha Temple in the Group of Monuments at Hampi was to serve as a center of pilgrimage and worship dedicated to Lord Shiva."
            }
        ]
    },
    {
        "id": "8f930011-a5cf-4d0c-8d39-c3f1622ed4d0",
        "image": "8f930011-a5cf-4d0c-8d39-c3f1622ed4d0.jpg",
        "conversations": [
            {
                "from": "human",
                "value": "What was the primary reason for the abandonment of Fatehpur Sikri?"
            },
            {
                "from": "gpt",
                "value": "The primary reason for the abandonment of Fatehpur Sikri was the scarcity of water, leading to the relocation of the capital to Agra."
            }
        ]
    },
    {
        "id": "79028361-ed77-402a-93b4-6d2aeabf4c8c",
        "image": "79028361-ed77-402a-93b4-6d2aeabf4c8c.jpg",
        "conversations": [
            {
                "from": "human",
                "value": "What is the religious significance of the temples in the Group of Monuments at Pattadakal?"
            },
            {
                "from": "gpt",
                "value": "The temples in the Group of Monuments at Pattadakal are dedicated to various Hindu gods and goddesses and served as centers of religious and royal patronage during the Chalukyan dynasty."
            }
        ]
    },
    {
        "id": "036fd5f2-9655-45e4-adca-051402894bf7",
        "image": "036fd5f2-9655-45e4-adca-051402894bf7.jpg",
        "conversations": [
            {
                "from": "human",
                "value": "What is the main deity worshipped in the Elephanta Caves?"
            },
            {
                "from": "gpt",
                "value": "The main deity worshipped in the Elephanta Caves is Lord Shiva, particularly in his form as Mahesha, the Lord of the Universe."
            }
        ]
    },
    {
        "id": "b9b285d8-526e-4cd5-ae98-cf361fbb37c8",
        "image": "b9b285d8-526e-4cd5-ae98-cf361fbb37c8.jpg",
        "conversations": [
            {
                "from": "human",
                "value": "What is the historical context behind the construction of the Great Living Chola Temples?"
            },
            {
                "from": "gpt",
                "value": "The Great Living Chola Temples were constructed during the Chola dynasty rule in South India, representing the pinnacle of Dravidian temple architecture and the Chola Empire's cultural and religious achievements."
            }
        ]
    },
    {
        "id": "71da360b-25c4-4ec1-a933-516f8b07fd9e",
        "image": "71da360b-25c4-4ec1-a933-516f8b07fd9e.jpg",
        "conversations": [
            {
                "from": "human",
                "value": "What is the main challenge faced by the inhabitants of Sundarbans National Park due to its geographical location?"
            },
            {
                "from": "gpt",
                "value": "The main challenge faced by the inhabitants of Sundarbans National Park due to its geographical location is the constant threat of tiger attacks and natural disasters such as cyclones and tidal surges."
            }
        ]
    },
    {
        "id": "601db7ec-b9f8-4256-989c-4c3f7637becb",
        "image": "601db7ec-b9f8-4256-989c-4c3f7637becb.jpg",
        "conversations": [
            {
                "from": "human",
                "value": "What is the best time of the year to witness the blooming of flowers in Valley of Flowers National Park?"
            },
            {
                "from": "gpt",
                "value": "The best time of the year to witness the blooming of flowers in Valley of Flowers National Park is from mid-July to mid-August, during the monsoon season."
            }
        ]
    },
    {
        "id": "7b301e7e-95b3-4a60-a026-0114ab402b6d",
        "image": "7b301e7e-95b3-4a60-a026-0114ab402b6d.jpg",
        "conversations": [
            {
                "from": "human",
                "value": "What is the architectural style of the stupas in the Buddhist Monuments at Sanchi?"
            },
            {
                "from": "gpt",
                "value": "The stupas in the Buddhist Monuments at Sanchi are primarily constructed in the early Buddhist architectural style, characterized by a simple hemispherical dome atop a raised platform, symbolizing the enlightened mind of the Buddha."
            }
        ]
    },
    {
        "id": "cf5356be-e535-4a01-bce8-9b5c88c10556",
        "image": "cf5356be-e535-4a01-bce8-9b5c88c10556.jpg",
        "conversations": [
            {
                "from": "human",
                "value": "What is the historical significance of Humayun's Tomb in Delhi?"
            },
            {
                "from": "gpt",
                "value": "Humayun's Tomb in Delhi is historically significant as it is the first garden-tomb on the Indian subcontinent and served as a prototype for later Mughal mausoleums, including the Taj Mahal."
            }
        ]
    },
    {
        "id": "fa21e62d-4ff7-4270-baeb-4a71eeb93943",
        "image": "fa21e62d-4ff7-4270-baeb-4a71eeb93943.jpg",
        "conversations": [
            {
                "from": "human",
                "value": "What is the main purpose of the Iron Pillar in the Qutb Minar complex?"
            },
            {
                "from": "gpt",
                "value": "The main purpose of the Iron Pillar in the Qutb Minar complex is believed to be a commemorative monument erected by Chandragupta II Vikramaditya to honor his military victories."
            }
        ]
    },
    {
        "id": "40a00851-1ac4-4438-ac4e-55fb4798b8e7",
        "image": "40a00851-1ac4-4438-ac4e-55fb4798b8e7.jpg",
        "conversations": [
            {
                "from": "human",
                "value": "What is the highest altitude reached by the Mountain Railways of India?"
            },
            {
                "from": "gpt",
                "value": "The highest altitude reached by the Mountain Railways of India is 2,076 meters above sea level at Ghum, West Bengal, making it the highest railway station in India."
            }
        ]
    },
    {
        "id": "e456e57e-7eaa-4ddc-9399-e91f5a6309af",
        "image": "e456e57e-7eaa-4ddc-9399-e91f5a6309af.jpg",
        "conversations": [
            {
                "from": "human",
                "value": "What is the significance of the Bodhi Tree in the Mahabodhi Temple Complex?"
            },
            {
                "from": "gpt",
                "value": "The Bodhi Tree in the Mahabodhi Temple Complex is believed to be the very spot where Gautama Buddha attained enlightenment, making it one of the most sacred sites in Buddhism."
            }
        ]
    },
    {
        "id": "81eec35a-c4ed-43f3-80fa-4f26151961d4",
        "image": "81eec35a-c4ed-43f3-80fa-4f26151961d4.jpg",
        "conversations": [
            {
                "from": "human",
                "value": "What is the age of the oldest rock painting found in the Rock Shelters of Bhimbetka?"
            },
            {
                "from": "gpt",
                "value": "The age of the oldest rock painting found in the Rock Shelters of Bhimbetka dates back to approximately 30,000 years ago, depicting scenes from prehistoric life."
            }
        ]
    },
    {
        "id": "0ad007ca-3098-44da-8603-d04253114a97",
        "image": "0ad007ca-3098-44da-8603-d04253114a97.jpg",
        "conversations": [
            {
                "from": "human",
                "value": "What is the historical event depicted on the central dome of Chhatrapati Shivaji Terminus?"
            },
            {
                "from": "gpt",
                "value": "The historical event depicted on the central dome of Chhatrapati Shivaji Terminus is the progress of Indian civilization under British colonial rule, symbolized by a figure holding a torch of progress."
            }
        ]
    },
    {
        "id": "33370f41-274d-4452-b180-8d225f2d2af1",
        "image": "33370f41-274d-4452-b180-8d225f2d2af1.jpg",
        "conversations": [
            {
                "from": "human",
                "value": "What is the significance of the Kalikamata Temple in the Champaner-Pavagadh Archaeological Park?"
            },
            {
                "from": "gpt",
                "value": "The Kalikamata Temple in the Champaner-Pavagadh Archaeological Park is dedicated to the goddess Kalika, an incarnation of Goddess Durga, and is believed to fulfill the wishes of devotees."
            }
        ]
    },
    {
        "id": "4270868d-8811-4b98-960d-dae8a988c0a7",
        "image": "4270868d-8811-4b98-960d-dae8a988c0a7.jpg",
        "conversations": [
            {
                "from": "human",
                "value": "What was the purpose of the Diwan-i-Khas in the Red Fort Complex?"
            },
            {
                "from": "gpt",
                "value": "The purpose of the Diwan-i-Khas in the Red Fort Complex was to serve as the hall of private audience where the Mughal emperor received select guests and held confidential meetings."
            }
        ]
    },
    {
        "id": "76b1da8e-4ae9-455b-b0f4-3d9735981249",
        "image": "76b1da8e-4ae9-455b-b0f4-3d9735981249.jpg",
        "conversations": [
            {
                "from": "human",
                "value": "What is the main astronomical instrument used in The Jantar Mantar for measuring time?"
            },
            {
                "from": "gpt",
                "value": "The main astronomical instrument used in The Jantar Mantar for measuring time is the sundial, known as the Samrat Yantra, which casts a shadow to indicate the time accurately."
            }
        ]
    },
    {
        "id": "c29fd124-816a-4305-92d5-3ca8b6230b14",
        "image": "c29fd124-816a-4305-92d5-3ca8b6230b14.jpg",
        "conversations": [
            {
                "from": "human",
                "value": "What is the main threat to the biodiversity of the Western Ghats?"
            },
            {
                "from": "gpt",
                "value": "The main threat to the biodiversity of the Western Ghats is habitat loss and fragmentation due to human activities such as deforestation, urbanization, and agricultural expansion."
            }
        ]
    },
    {
        "id": "a8aa5958-04aa-4eb4-85ac-9e4bf7f8d2f6",
        "image": "a8aa5958-04aa-4eb4-85ac-9e4bf7f8d2f6.jpg",
        "conversations": [
            {
                "from": "human",
                "value": "What is the main defensive feature shared by all the Hill Forts of Rajasthan?"
            },
            {
                "from": "gpt",
                "value": "The main defensive feature shared by all the Hill Forts of Rajasthan is their strategic hilltop location, providing natural protection against enemy invasions."
            }
        ]
    },
    {
        "id": "4d918768-b70c-4acb-b049-73a42a0bddc4",
        "image": "4d918768-b70c-4acb-b049-73a42a0bddc4.jpg",
        "conversations": [
            {
                "from": "human",
                "value": "What is the architectural significance of the stepwell in Rani-ki-Vav?"
            },
            {
                "from": "gpt",
                "value": "The architectural significance of the stepwell in Rani-ki-Vav lies in its intricate carvings, which depict various deities, mythological scenes, and Hindu religious motifs, making it a masterpiece of Maru-Gurjara architecture."
            }
        ]
    },
    {
        "id": "2e90dcf5-6d08-415f-89fd-233a5727b881",
        "image": "2e90dcf5-6d08-415f-89fd-233a5727b881.jpg",
        "conversations": [
            {
                "from": "human",
                "value": "What is the main threat to the habitat of the snow leopard in the Great Himalayan National Park?"
            },
            {
                "from": "gpt",
                "value": "The main threat to the habitat of the snow leopard in the Great Himalayan National Park is poaching, retaliatory killings by herders, and habitat degradation due to livestock grazing and infrastructure development."
            }
        ]
    },
    {
        "id": "3de82dc5-c793-4764-98dd-8497d30583fc",
        "image": "3de82dc5-c793-4764-98dd-8497d30583fc.jpg",
        "conversations": [
            {
                "from": "human",
                "value": "What is the subject of the inscriptions found in the Archaeological Site of Nalanda Mahavihara?"
            },
            {
                "from": "gpt",
                "value": "The inscriptions found in the Archaeological Site of Nalanda Mahavihara primarily depict various aspects of Buddhist philosophy, history, and education, providing valuable insights into the intellectual and cultural life of ancient India."
            }
        ]
    },
    {
        "id": "f842719b-9806-4796-bc6a-d868775ac623",
        "image": "f842719b-9806-4796-bc6a-d868775ac623.jpg",
        "conversations": [
            {
                "from": "human",
                "value": "What is the traditional belief associated with the name 'Khangchendzonga'?"
            },
            {
                "from": "gpt",
                "value": "The traditional belief associated with the name 'Khangchendzonga' is that it is the abode of the guardian deity of Sikkim, protecting the land and its people."
            }
        ]
    },
    {
        "id": "3ea2c156-b9eb-4043-a9f1-b46976936ae1",
        "image": "3ea2c156-b9eb-4043-a9f1-b46976936ae1.jpg",
        "conversations": [
            {
                "from": "human",
                "value": "What is the main feature that distinguishes the architectural work of Le Corbusier?"
            },
            {
                "from": "gpt",
                "value": "The main feature that distinguishes the architectural work of Le Corbusier is the use of open floor plans, modular design principles, and reinforced concrete structures, reflecting the principles of modernist architecture."
            }
        ]
    },
    {
        "id": "67056c58-56f9-491d-ac2b-7109b3318483",
        "image": "67056c58-56f9-491d-ac2b-7109b3318483.jpg",
        "conversations": [
            {
                "from": "human",
                "value": "What is the unique architectural feature of the Pols in the Historic City of Ahmadabad?"
            },
            {
                "from": "gpt",
                "value": "The unique architectural feature of the Pols in the Historic City of Ahmadabad is their narrow lanes and intricate wooden facades, reflecting the traditional Gujarati architectural style and providing a sense of community and security."
            }
        ]
    },
    {
        "id": "4bbe9bdc-fea0-43bf-903d-a546dffce0f0",
        "image": "4bbe9bdc-fea0-43bf-903d-a546dffce0f0.jpg",
        "conversations": [
            {
                "from": "human",
                "value": "What is the historical significance of the Victorian Gothic and Art Deco Ensembles of Mumbai?"
            },
            {
                "from": "gpt",
                "value": "The Victorian Gothic and Art Deco Ensembles of Mumbai are historically significant as they represent the architectural and urban planning innovations during the British colonial period and the early 20th century, reflecting the city's economic and cultural prosperity."
            }
        ]
    },
    {
        "id": "e659a416-db44-4d61-aab0-65ba3f10b8e6",
        "image": "e659a416-db44-4d61-aab0-65ba3f10b8e6.jpg",
        "conversations": [
            {
                "from": "human",
                "value": "What is the main festival celebrated within the walled city of Jaipur?"
            },
            {
                "from": "gpt",
                "value": "The main festival celebrated within the walled city of Jaipur is the Gangaur festival, dedicated to the goddess Gauri, celebrated with great fervor by womenfolk, showcasing Rajasthan's rich cultural heritage and traditions."
            }
        ]
    },
    {
        "id": "ca9c513f-794c-47d3-8554-885c588a7a7a",
        "image": "ca9c513f-794c-47d3-8554-885c588a7a7a.jpg",
        "conversations": [
            {
                "from": "human",
                "value": "What is the architectural style of the Kakatiya Rudreshwara Temple?"
            },
            {
                "from": "gpt",
                "value": "The architectural style of the Kakatiya Rudreshwara Temple is predominantly Kakatiyan, characterized by intricate carvings, detailed sculptures, and the use of locally available red sandstone, showcasing the artistic and engineering prowess of the Kakatiya dynasty."
            }
        ]
    },
    {
        "id": "ac7217cb-ac8b-48ac-89a9-6a2f36b36fd4",
        "image": "ac7217cb-ac8b-48ac-89a9-6a2f36b36fd4.jpg",
        "conversations": [
            {
                "from": "human",
                "value": "What was the main source of water supply in Dholavira?"
            },
            {
                "from": "gpt",
                "value": "The main source of water supply in Dholavira was an elaborate system of reservoirs and channels."
            }
        ]
    },
    {
        "id": "51bed6e0-c3aa-4807-ab66-825e8a8ad251",
        "image": "51bed6e0-c3aa-4807-ab66-825e8a8ad251.jpg",
        "conversations": [
            {
                "from": "human",
                "value": "What is the significance of Santiniketan in Indian cultural history?"
            },
            {
                "from": "gpt",
                "value": "Santiniketan is significant in Indian cultural history as the home of Visva-Bharati University, founded by Rabindranath Tagore."
            }
        ]
    },
    {
        "id": "6f413891-07b9-4329-9197-2eb7d839a793",
        "image": "6f413891-07b9-4329-9197-2eb7d839a793.jpg",
        "conversations": [
            {
                "from": "human",
                "value": "What distinguishes the architectural style of the Hoysala temples?"
            },
            {
                "from": "gpt",
                "value": "The architectural style of the Hoysala temples is distinguished by intricate carvings and sculptures, particularly of gods and goddesses."
            }
        ]
    },
    {
        "id": "1655b362-e86f-43f5-bfa9-bfebdb783a10",
        "image": "1655b362-e86f-43f5-bfa9-bfebdb783a10.jpg",
        "conversations": [
            {
                "from": "human",
                "value": "What is the predominant material used in the construction of the temples at Bishnupur?"
            },
            {
                "from": "gpt",
                "value": "The predominant material used in the construction of the temples at Bishnupur is laterite stone."
            }
        ]
    },
    {
        "id": "3475c04f-72d1-4a8b-b0d0-8e681436f072",
        "image": "3475c04f-72d1-4a8b-b0d0-8e681436f072.jpg",
        "conversations": [
            {
                "from": "human",
                "value": "What are the main themes depicted in the murals of Mattancherry Palace?"
            },
            {
                "from": "gpt",
                "value": "The main themes depicted in the murals of Mattancherry Palace include scenes from the Ramayana and Mahabharata."
            }
        ]
    },
    {
        "id": "cc8e0901-31cb-4e33-9690-55dbd72067cf",
        "image": "cc8e0901-31cb-4e33-9690-55dbd72067cf.jpg",
        "conversations": [
            {
                "from": "human",
                "value": "What is the main architectural feature of the Jahaz Mahal in Mandu?"
            },
            {
                "from": "gpt",
                "value": "The main architectural feature of the Jahaz Mahal in Mandu is its boat-like shape, giving it the name 'Ship Palace'."
            }
        ]
    },
    {
        "id": "1adba67a-73a8-4632-8206-865ab88dc714",
        "image": "1adba67a-73a8-4632-8206-865ab88dc714.jpg",
        "conversations": [
            {
                "from": "human",
                "value": "What event in Buddha's life is associated with the ancient Buddhist site at Sarnath?"
            },
            {
                "from": "gpt",
                "value": "The ancient Buddhist site at Sarnath is associated with Buddha's first sermon, known as the 'Turning of the Wheel of Dharma'."
            }
        ]
    },
    {
        "id": "8a2b1d44-9caf-4dbe-ac97-f1ca8078ef4c",
        "image": "8a2b1d44-9caf-4dbe-ac97-f1ca8078ef4c.jpg",
        "conversations": [
            {
                "from": "human",
                "value": "What is the significance of the sarovar (sacred pool) at Sri Harimandir Sahib?"
            },
            {
                "from": "gpt",
                "value": "The sarovar at Sri Harimandir Sahib symbolizes spiritual purification and is believed to have healing properties."
            }
        ]
    },
    {
        "id": "80a80ff4-2873-4e35-9334-700a83e197e8",
        "image": "80a80ff4-2873-4e35-9334-700a83e197e8.jpg",
        "conversations": [
            {
                "from": "human",
                "value": "What is the main cultural significance of Majuli island?"
            },
            {
                "from": "gpt",
                "value": "Majuli island is culturally significant as the hub of Assamese Vaishnavite culture, with numerous satras (monasteries) dedicated to the practice of Sattriya dance and music."
            }
        ]
    },
    {
        "id": "242e59b2-c5a0-4b25-b119-7f3a54de4b89",
        "image": "242e59b2-c5a0-4b25-b119-7f3a54de4b89.jpg",
        "conversations": [
            {
                "from": "human",
                "value": "What is the main threat to the biodiversity of Namdapha National Park?"
            },
            {
                "from": "gpt",
                "value": "The main threat to the biodiversity of Namdapha National Park is poaching and habitat destruction."
            }
        ]
    },
    {
        "id": "530af9ca-b3fc-4111-ae0e-7d8834e4d65d",
        "image": "530af9ca-b3fc-4111-ae0e-7d8834e4d65d.jpg",
        "conversations": [
            {
                "from": "human",
                "value": "What is the main habitat of the wild ass species in the Little Rann of Kutch?"
            },
            {
                "from": "gpt",
                "value": "The main habitat of the wild ass species in the Little Rann of Kutch is the vast saline desert."
            }
        ]
    },
    {
        "id": "72f54754-22a1-49e7-9d4a-2e5b5b60ac47",
        "image": "72f54754-22a1-49e7-9d4a-2e5b5b60ac47.jpg",
        "conversations": [
            {
                "from": "human",
                "value": "What is the main floral diversity found in Neora Valley National Park?"
            },
            {
                "from": "gpt",
                "value": "Neora Valley National Park is known for its rich floral diversity, including rhododendrons, orchids, and medicinal plants."
            }
        ]
    },
    {
        "id": "ff6e858a-05bc-4c4b-8b3c-cfe0fdd9769e",
        "image": "ff6e858a-05bc-4c4b-8b3c-cfe0fdd9769e.jpg",
        "conversations": [
            {
                "from": "human",
                "value": "What is the main adaptation of wildlife in Desert National Park to survive extreme temperatures?"
            },
            {
                "from": "gpt",
                "value": "The main adaptation of wildlife in Desert National Park is nocturnal activity to avoid extreme daytime temperatures."
            }
        ]
    },
    {
        "id": "fde91580-a847-4ed0-9fab-eaa4a9d554a3",
        "image": "fde91580-a847-4ed0-9fab-eaa4a9d554a3.jpg",
        "conversations": [
            {
                "from": "human",
                "value": "What was the main commodity traded along the Silk Road Sites in India?"
            },
            {
                "from": "gpt",
                "value": "The main commodity traded along the Silk Road Sites in India was silk, which gave the trade route its name."
            }
        ]
    },
    {
        "id": "c85542d1-534c-4f63-8cca-7ab1ecab635f",
        "image": "c85542d1-534c-4f63-8cca-7ab1ecab635f.jpg",
        "conversations": [
            {
                "from": "human",
                "value": "What is the significance of the Charminar in the history of Hyderabad?"
            },
            {
                "from": "gpt",
                "value": "The Charminar is a symbol of Hyderabad and was built to commemorate the end of a deadly plague epidemic."
            }
        ]
    },
    {
        "id": "5d99f81a-e31b-4126-beb8-151d9d27b05f",
        "image": "5d99f81a-e31b-4126-beb8-151d9d27b05f.jpg",
        "conversations": [
            {
                "from": "human",
                "value": "What is the primary design element of the Mughal Gardens in Kashmir?"
            },
            {
                "from": "gpt",
                "value": "The primary design element of the Mughal Gardens in Kashmir is the use of terraces and water channels."
            }
        ]
    },
    {
        "id": "57e7b2b4-53c9-4411-86b1-adbf4ae7398f",
        "image": "57e7b2b4-53c9-4411-86b1-adbf4ae7398f.jpg",
        "conversations": [
            {
                "from": "human",
                "value": "What are the main architectural influences seen in the heritage buildings of Delhi?"
            },
            {
                "from": "gpt",
                "value": "The main architectural influences seen in the heritage buildings of Delhi include Mughal, British, and Persian styles."
            }
        ]
    },
    {
        "id": "966ffeb7-3e13-4ebe-a426-1f321905be44",
        "image": "966ffeb7-3e13-4ebe-a426-1f321905be44.jpg",
        "conversations": [
            {
                "from": "human",
                "value": "What architectural style characterizes the forts of the Deccan Sultanate?"
            },
            {
                "from": "gpt",
                "value": "The forts of the Deccan Sultanate are characterized by a blend of Persian, Indian, and Islamic architectural styles."
            }
        ]
    },
    {
        "id": "3e75d14e-1885-48e9-9042-0eb9e1f35bf7",
        "image": "3e75d14e-1885-48e9-9042-0eb9e1f35bf7.jpg",
        "conversations": [
            {
                "from": "human",
                "value": "What was the main purpose of the Cellular Jail during British rule?"
            },
            {
                "from": "gpt",
                "value": "The main purpose of the Cellular Jail was to imprison political dissidents and freedom fighters."
            }
        ]
    },
    {
        "id": "d6b3564a-6acb-4d62-ad16-6f431cb000ae",
        "image": "d6b3564a-6acb-4d62-ad16-6f431cb000ae.jpg",
        "conversations": [
            {
                "from": "human",
                "value": "What are the main regions known for producing iconic saree weaving in India?"
            },
            {
                "from": "gpt",
                "value": "The main regions known for producing iconic saree weaving in India include Banaras, Kanchipuram, and Paithani."
            }
        ]
    },
    {
        "id": "ccf56deb-44c7-49c2-b89a-ccfd81330b7c",
        "image": "ccf56deb-44c7-49c2-b89a-ccfd81330b7c.jpg",
        "conversations": [
            {
                "from": "human",
                "value": "What are the main features of the Apatani cultural landscape?"
            },
            {
                "from": "gpt",
                "value": "The main features of the Apatani cultural landscape include the unique practices of terrace farming and nose plugs worn by women."
            }
        ]
    },
    {
        "id": "9d7f7e51-2c31-4b8f-a709-d503b650e04d",
        "image": "9d7f7e51-2c31-4b8f-a709-d503b650e04d.jpg",
        "conversations": [
            {
                "from": "human",
                "value": "What is the significance of the Sri Ranganathaswamy Temple in Srirangam?"
            },
            {
                "from": "gpt",
                "value": "The Sri Ranganathaswamy Temple in Srirangam is one of the largest functioning Hindu temples in the world and is dedicated to Lord Vishnu."
            }
        ]
    },
    {
        "id": "df23ce7f-c78f-42af-8d1b-630efe482fb4",
        "image": "df23ce7f-c78f-42af-8d1b-630efe482fb4.jpg",
        "conversations": [
            {
                "from": "human",
                "value": "What is the historical significance of the monuments in Srirangapatna?"
            },
            {
                "from": "gpt",
                "value": "The monuments in Srirangapatna are associated with the reign of Tipu Sultan and the battles fought during the British colonial period."
            }
        ]
    },
    {
        "id": "ba74216d-ab7c-4455-9f9f-97ca288a9ed9",
        "image": "ba74216d-ab7c-4455-9f9f-97ca288a9ed9.jpg",
        "conversations": [
            {
                "from": "human",
                "value": "What is the main ecological importance of Chilika Lake?"
            },
            {
                "from": "gpt",
                "value": "The main ecological importance of Chilika Lake is as a vital habitat for migratory birds and endangered species such as the Irrawaddy dolphin."
            }
        ]
    },
    {
        "id": "47d99108-2874-413a-8df2-307f4eb900a7",
        "image": "47d99108-2874-413a-8df2-307f4eb900a7.jpg",
        "conversations": [
            {
                "from": "human",
                "value": "What is the main architectural feature of Padmanabhapuram Palace?"
            },
            {
                "from": "gpt",
                "value": "The main architectural feature of Padmanabhapuram Palace is its wooden construction, showcasing traditional Kerala architecture."
            }
        ]
    },
    {
        "id": "c8c3bfa9-d0de-440d-9fb3-6a5e3c188e55",
        "image": "c8c3bfa9-d0de-440d-9fb3-6a5e3c188e55.jpg",
        "conversations": [
            {
                "from": "human",
                "value": "What were the main principles of Satyagraha advocated in the freedom movement?"
            },
            {
                "from": "gpt",
                "value": "The main principles of Satyagraha advocated in the freedom movement were non-violence, civil disobedience, and truth."
            }
        ]
    },
    {
        "id": "1d85fe26-b0ab-4ed9-b23d-3dd46380b48c",
        "image": "1d85fe26-b0ab-4ed9-b23d-3dd46380b48c.jpg",
        "conversations": [
            {
                "from": "human",
                "value": "What is the main defensive structure in Thembang Fortified Village?"
            },
            {
                "from": "gpt",
                "value": "The main defensive structure in Thembang Fortified Village is its stone walls and watchtowers."
            }
        ]
    },
    {
        "id": "3235bb2b-9a37-403f-8bb0-1bfcbccfc1fb",
        "image": "3235bb2b-9a37-403f-8bb0-1bfcbccfc1fb.jpg",
        "conversations": [
            {
                "from": "human",
                "value": "What is the main threat to the unique flora and fauna of Narcondam Island?"
            },
            {
                "from": "gpt",
                "value": "The main threat to the unique flora and fauna of Narcondam Island is habitat destruction caused by invasive species."
            }
        ]
    },
    {
        "id": "f82e2dc2-2862-40ad-b625-84bde7c52979",
        "image": "f82e2dc2-2862-40ad-b625-84bde7c52979.jpg",
        "conversations": [
            {
                "from": "human",
                "value": "What is the main significance of the Moidams in Ahom culture?"
            },
            {
                "from": "gpt",
                "value": "The main significance of the Moidams in Ahom culture is as burial mounds for Ahom royalty and nobility."
            }
        ]
    },
    {
        "id": "98dc5cdd-06c8-47df-956f-22771045d9ef",
        "image": "98dc5cdd-06c8-47df-956f-22771045d9ef.jpg",
        "conversations": [
            {
                "from": "human",
                "value": "What is the main architectural style of the temples in Ekamra Kshetra?"
            },
            {
                "from": "gpt",
                "value": "The main architectural style of the temples in Ekamra Kshetra is Kalinga architecture, characterized by pyramidical towers and intricate carvings."
            }
        ]
    },
    {
        "id": "388b75ac-7b54-4db5-9653-e953bbe76598",
        "image": "388b75ac-7b54-4db5-9653-e953bbe76598.jpg",
        "conversations": [
            {
                "from": "human",
                "value": "What is the main archaeological find at the Neolithic Settlement of Burzahom?"
            },
            {
                "from": "gpt",
                "value": "The main archaeological find at the Neolithic Settlement of Burzahom is evidence of early agriculture and domestication of animals."
            }
        ]
    },
    {
        "id": "80139fd1-e4cc-4184-ab8f-da42a89ec62c",
        "image": "80139fd1-e4cc-4184-ab8f-da42a89ec62c.jpg",
        "conversations": [
            {
                "from": "human",
                "value": "What is the main evidence of Lothal being a Harappan port-town?"
            },
            {
                "from": "gpt",
                "value": "The main evidence of Lothal being a Harappan port-town is its dockyard, which was used for maritime trade."
            }
        ]
    },
    {
        "id": "f5b5d7c3-ec91-49f1-aa3d-beb417f85b05",
        "image": "f5b5d7c3-ec91-49f1-aa3d-beb417f85b05.jpg",
        "conversations": [
            {
                "from": "human",
                "value": "What is the highest railway station reached by the Mountain Railways of India (Extension)?"
            },
            {
                "from": "gpt",
                "value": "The highest railway station reached by the Mountain Railways of India (Extension) is Ghum station in West Bengal."
            }
        ]
    },
    {
        "id": "f577ae23-0313-4ca2-bb04-1bb112444add",
        "image": "f577ae23-0313-4ca2-bb04-1bb112444add.jpg",
        "conversations": [
            {
                "from": "human",
                "value": "What is the main architectural feature of the mansions in Chettinad?"
            },
            {
                "from": "gpt",
                "value": "The main architectural feature of the mansions in Chettinad is their grandeur and elaborate woodwork."
            }
        ]
    },
    {
        "id": "a5cb64f7-995b-4819-8188-4a6438af5c0a",
        "image": "a5cb64f7-995b-4819-8188-4a6438af5c0a.jpg",
        "conversations": [
            {
                "from": "human",
                "value": "What is the central theme of the Baha'i House of Worship's architectural design?"
            },
            {
                "from": "gpt",
                "value": "The central theme of the Baha'i House of Worship's architectural design is unity, with its lotus-shaped structure symbolizing the oneness of humanity."
            }
        ]
    },
    {
        "id": "a692c17b-edd8-48fa-9fef-254a845e59f1",
        "image": "a692c17b-edd8-48fa-9fef-254a845e59f1.jpg",
        "conversations": [
            {
                "from": "human",
                "value": "What are the main architectural elements that evolved in Aihole-Badami-Pattadakal temple complex?"
            },
            {
                "from": "gpt",
                "value": "The main architectural elements that evolved in Aihole-Badami-Pattadakal temple complex include the vimana (tower), mandapa (hall), and intricate sculptures."
            }
        ]
    },
    {
        "id": "2636b9d1-4106-420d-9dba-a46bf3a4c048",
        "image": "2636b9d1-4106-420d-9dba-a46bf3a4c048.jpg",
        "conversations": [
            {
                "from": "human",
                "value": "What is the main cultural practice of the inhabitants of the Cold Desert Cultural Landscape?"
            },
            {
                "from": "gpt",
                "value": "The main cultural practice of the inhabitants of the Cold Desert Cultural Landscape is transhumance, where they migrate with their livestock seasonally."
            }
        ]
    },
    {
        "id": "d686fe0d-add5-44c6-98e4-b51e6508c500",
        "image": "d686fe0d-add5-44c6-98e4-b51e6508c500.jpg",
        "conversations": [
            {
                "from": "human",
                "value": "What was the primary purpose of the Grand Trunk Road during ancient times?"
            },
            {
                "from": "gpt",
                "value": "The primary purpose of the Grand Trunk Road during ancient times was to facilitate trade and communication between different regions of the Indian subcontinent."
            }
        ]
    },
    {
        "id": "493933cc-1107-4d0b-a5d6-30f39d73c387",
        "image": "493933cc-1107-4d0b-a5d6-30f39d73c387.jpg",
        "conversations": [
            {
                "from": "human",
                "value": "What is the main habitat of the endangered sangai deer in Keibul Lamjao Conservation Area?"
            },
            {
                "from": "gpt",
                "value": "The main habitat of the endangered sangai deer in Keibul Lamjao Conservation Area is the floating marshy vegetation known as phumdis."
            }
        ]
    },
    {
        "id": "11e3dc25-08c0-4260-acac-2f896a50ecb8",
        "image": "11e3dc25-08c0-4260-acac-2f896a50ecb8.jpg",
        "conversations": [
            {
                "from": "human",
                "value": "What is the main biodiversity hotspot found in Garo Hills Conservation Area?"
            },
            {
                "from": "gpt",
                "value": "The main biodiversity hotspot found in Garo Hills Conservation Area is Nokrek Biosphere Reserve, known for its rich floral and faunal diversity."
            }
        ]
    },
    {
        "id": "477ad064-758f-4703-8ebb-adfd8796bdda",
        "image": "477ad064-758f-4703-8ebb-adfd8796bdda.jpg",
        "conversations": [
            {
                "from": "human",
                "value": "What is the main architectural feature of the Jehangir Mahal in Orchha?"
            },
            {
                "from": "gpt",
                "value": "The main architectural feature of the Jehangir Mahal in Orchha is its intricate facade adorned with elaborate carvings and motifs."
            }
        ]
    },
    {
        "id": "98a25caa-ad18-44a7-9a4c-750a05ea1da1",
        "image": "98a25caa-ad18-44a7-9a4c-750a05ea1da1.jpg",
        "conversations": [
            {
                "from": "human",
                "value": "What is the cultural significance of the ghats along the River Ganges in Varanasi?"
            },
            {
                "from": "gpt",
                "value": "The ghats along the River Ganges in Varanasi hold cultural significance as sites for religious rituals, ceremonies, and cremation."
            }
        ]
    },
    {
        "id": "27796da6-b43b-486b-ab3d-3efca351b2db",
        "image": "27796da6-b43b-486b-ab3d-3efca351b2db.jpg",
        "conversations": [
            {
                "from": "human",
                "value": "What is the main deity worshipped in the temples of Kanchipuram?"
            },
            {
                "from": "gpt",
                "value": "The main deity worshipped in the temples of Kanchipuram is Lord Shiva, along with various forms of Goddess Parvati."
            }
        ]
    },
    {
        "id": "281cd9d8-61ba-4027-b861-a4b2c5361ce0",
        "image": "281cd9d8-61ba-4027-b861-a4b2c5361ce0.jpg",
        "conversations": [
            {
                "from": "human",
                "value": "What are the main types of megalithic structures found in Hire Benakal?"
            },
            {
                "from": "gpt",
                "value": "The main types of megalithic structures found in Hire Benakal are dolmens, cists, and menhirs."
            }
        ]
    },
    {
        "id": "00947170-e972-4d5a-acf3-72f64a3abb43",
        "image": "00947170-e972-4d5a-acf3-72f64a3abb43.jpg",
        "conversations": [
            {
                "from": "human",
                "value": "What is the geological feature that attracts tourists to Bhedaghat-Lametaghat?"
            },
            {
                "from": "gpt",
                "value": "The geological feature that attracts tourists to Bhedaghat-Lametaghat is the marble rocks, carved by the Narmada River, creating stunning landscapes."
            }
        ]
    },
    {
        "id": "6370b6ea-c320-4ac6-8872-e59bfc305f70",
        "image": "6370b6ea-c320-4ac6-8872-e59bfc305f70.jpg",
        "conversations": [
            {
                "from": "human",
                "value": "What is the main wildlife species targeted for conservation in Satpura Tiger Reserve?"
            },
            {
                "from": "gpt",
                "value": "The main wildlife species targeted for conservation in Satpura Tiger Reserve include Bengal tigers, leopards, and Indian gaur."
            }
        ]
    },
    {
        "id": "f03fed1a-8742-4ed6-a479-1352bacda4d2",
        "image": "f03fed1a-8742-4ed6-a479-1352bacda4d2.jpg",
        "conversations": [
            {
                "from": "human",
                "value": "What are the main defensive features of Maratha military architecture?"
            },
            {
                "from": "gpt",
                "value": "The main defensive features of Maratha military architecture include bastions, fortified gateways, and moats."
            }
        ]
    },
    {
        "id": "d31ae51d-2d0a-4e00-afa7-bb3500f1a036",
        "image": "d31ae51d-2d0a-4e00-afa7-bb3500f1a036.jpg",
        "conversations": [
            {
                "from": "human",
                "value": "What are the main subjects depicted in the geoglyphs of the Konkan Region?"
            },
            {
                "from": "gpt",
                "value": "The main subjects depicted in the geoglyphs of the Konkan Region are animals, humans, and geometric patterns."
            }
        ]
    },
    {
        "id": "d3f05640-ccac-4a41-a5b9-ade12e712323",
        "image": "d3f05640-ccac-4a41-a5b9-ade12e712323.jpg",
        "conversations": [
            {
                "from": "human",
                "value": "What is the main material used in the construction of the living root bridges?"
            },
            {
                "from": "gpt",
                "value": "The main material used in the construction of the living root bridges is the aerial roots of the Indian rubber tree (Ficus elastica)."
            }
        ]
    },
    {
        "id": "6bcc3bb1-a3e5-4e71-97e0-7834ba4e041c",
        "image": "6bcc3bb1-a3e5-4e71-97e0-7834ba4e041c.jpg",
        "conversations": [
            {
                "from": "human",
                "value": "What is the significance of the monolithic Nandi bull at Lepakshi?"
            },
            {
                "from": "gpt",
                "value": "The significance of the monolithic Nandi bull at Lepakshi lies in its association with Lord Shiva and the grandeur of Vijayanagara art."
            }
        ]
    },
    {
        "id": "dfdc8d9d-3c8a-4ce9-9535-da462869f009",
        "image": "dfdc8d9d-3c8a-4ce9-9535-da462869f009.jpg",
        "conversations": [
            {
                "from": "human",
                "value": "What is the main feature of the architecture of Sun Temple in Modhera?"
            },
            {
                "from": "gpt",
                "value": "The main feature of the architecture of Sun Temple in Modhera is its precision in solar alignment, designed to capture the first rays of the sun during the equinox."
            }
        ]
    },
    {
        "id": "8f9ba466-4618-4e9a-bd80-c86f220bab97",
        "image": "8f9ba466-4618-4e9a-bd80-c86f220bab97.jpg",
        "conversations": [
            {
                "from": "human",
                "value": "What is the estimated number of rock-cut sculptures present in Unakoti?"
            },
            {
                "from": "gpt",
                "value": "The estimated number of rock-cut sculptures present in Unakoti is around one crore (ten million)."
            }
        ]
    },
    {
        "id": "b55cb512-da94-4041-a51d-28581fb0de40",
        "image": "b55cb512-da94-4041-a51d-28581fb0de40.jpg",
        "conversations": [
            {
                "from": "human",
                "value": "What is the main archaeological find that dates Vadnagar as a historic town?"
            },
            {
                "from": "gpt",
                "value": "The main archaeological find that dates Vadnagar as a historic town is the discovery of a Buddhist monastery complex, indicating its ancient roots."
            }
        ]
    },
    {
        "id": "b29ffb6b-dfc2-4dd8-8508-646e0b2d3dac",
        "image": "b29ffb6b-dfc2-4dd8-8508-646e0b2d3dac.jpg",
        "conversations": [
            {
                "from": "human",
                "value": "What is the primary architectural feature shared by the coastal fortifications along the Konkan Coast?"
            },
            {
                "from": "gpt",
                "value": "The primary architectural feature shared by the coastal fortifications along the Konkan Coast is their strategic location overlooking the Arabian Sea."
            }
        ]
    },
    {
        "id": "c3fe9bed-0a1a-4a45-a05a-f114a489ddfc",
        "image": "c3fe9bed-0a1a-4a45-a05a-f114a489ddfc.jpg",
        "conversations": [
            {
                "from": "human",
                "value": "What is the main architectural feature of the historic ensemble in Dhamnar?"
            },
            {
                "from": "gpt",
                "value": "The main architectural feature of the historic ensemble in Dhamnar is its fortified walls and bastions, reflecting its defensive character."
            }
        ]
    },
    {
        "id": "0e3a1434-f7a1-4b4f-99ab-6902c632ae06",
        "image": "0e3a1434-f7a1-4b4f-99ab-6902c632ae06.jpg",
        "conversations": [
            {
                "from": "human",
                "value": "What is the main artistic motif seen in the Gond monuments of Ramnagar?"
            },
            {
                "from": "gpt",
                "value": "The main artistic motif seen in the Gond monuments of Ramnagar is the depiction of animals and human figures in vibrant colors."
            }
        ]
    },
    {
        "id": "146ed8ec-82c9-4be9-8201-2b621571181f",
        "image": "146ed8ec-82c9-4be9-8201-2b621571181f.jpg",
        "conversations": [
            {
                "from": "human",
                "value": "What is the main feature of the shikhara (spire) of Bhojeshwar Mahadev Temple?"
            },
            {
                "from": "gpt",
                "value": "The main feature of the shikhara (spire) of Bhojeshwar Mahadev Temple is its unfinished state, suggesting ambitious architectural plans."
            }
        ]
    },
    {
        "id": "191833c1-aa94-49ce-a16e-c75cde27b542",
        "image": "191833c1-aa94-49ce-a16e-c75cde27b542.jpg",
        "conversations": [
            {
                "from": "human",
                "value": "What is the main architectural style of Gwalior Fort?"
            },
            {
                "from": "gpt",
                "value": "The main architectural style of Gwalior Fort is a blend of Rajput and Mughal styles, reflecting its rich history of successive rulers."
            }
        ]
    }
]